mfa_ua/__init__.py
mfa_ua/monte_carlo/__init__.py
mfa_ua/monte_carlo/monte_carlo.py
mfa_ua/monte_carlo/parameters.py
mfa_ua/monte_carlo/sampler.py
mfa_ua/parameter_estimation/__init__.py
mfa_ua/parameter_estimation/lognorm_fit.py
mfa_ua/parameter_estimation/right_skewed_lognorm.py
mfa_ua/sensitivity_analysis/__init__.py
mfa_ua/sensitivity_analysis/get_sensitivities.py
mfa_ua/sensitivity_analysis/sensitivity_heatmap.py
mfa_ua-0.1.0.dist-info/LICENSE
mfa_ua-0.1.0.dist-info/METADATA
mfa_ua-0.1.0.dist-info/WHEEL
mfa_ua-0.1.0.dist-info/top_level.txt
mfa_ua-0.1.0.dist-info/RECORD
